zoomeyeai/__init__.py
zoomeyeai/cli.py
zoomeyeai/config.py
zoomeyeai/core.py
zoomeyeai/file.py
zoomeyeai/plotlib.py
zoomeyeai/sdk.py
zoomeyeai/show.py
zoomeyeai/tools.py
zoomeyeai-3.0.1.dist-info/LICENSE
zoomeyeai-3.0.1.dist-info/METADATA
zoomeyeai-3.0.1.dist-info/WHEEL
zoomeyeai-3.0.1.dist-info/entry_points.txt
zoomeyeai-3.0.1.dist-info/top_level.txt
zoomeyeai-3.0.1.dist-info/RECORD
